{
    "os": "Linux-6.2.0-32-generic-x86_64-with-glibc2.37",
    "python": "3.9.18",
    "heartbeatAt": "2024-03-17T04:08:44.715772",
    "startedAt": "2024-03-17T04:08:44.105435",
    "docker": null,
    "cuda": null,
    "args": [
        "--trainval_artifact",
        "trainval_data.csv:latest",
        "--val_size",
        "0.2",
        "--random_seed",
        "42",
        "--stratify_by",
        "neighbourhood_group",
        "--rf_config",
        "/home/falcon/Project-Build-an-ML-Pipeline-Starter/multirun/2024-03-16/22-07-24/0/rf_config.json",
        "--max_tfidf_features",
        "5",
        "--output_artifact",
        "random_forest_export"
    ],
    "state": "running",
    "program": "/home/falcon/Project-Build-an-ML-Pipeline-Starter/src/train_random_forest/run.py",
    "codePath": "src/train_random_forest/run.py",
    "git": {
        "remote": "https://github.com/ebs-well/Project-Build-an-ML-Pipeline-Starter.git",
        "commit": "077621b0ed54d88e8c2f5ef3dea7b725c4ea7c98"
    },
    "email": null,
    "root": "/home/falcon/Project-Build-an-ML-Pipeline-Starter",
    "host": "msiFlip",
    "username": "falcon",
    "executable": "/home/falcon/miniconda3/envs/mlflow-d6c04384fb9356865b6d231fc3cbd1b1b9b4863e/bin/python",
    "cpu_count": 4,
    "cpu_count_logical": 8,
    "cpu_freq": {
        "current": 1200.856125,
        "min": 400.0,
        "max": 4500.0
    },
    "cpu_freq_per_core": [
        {
            "current": 924.274,
            "min": 400.0,
            "max": 4500.0
        },
        {
            "current": 1296.117,
            "min": 400.0,
            "max": 4500.0
        },
        {
            "current": 1230.014,
            "min": 400.0,
            "max": 4500.0
        },
        {
            "current": 1289.846,
            "min": 400.0,
            "max": 4500.0
        },
        {
            "current": 567.522,
            "min": 400.0,
            "max": 4500.0
        },
        {
            "current": 2500.0,
            "min": 400.0,
            "max": 4500.0
        },
        {
            "current": 561.715,
            "min": 400.0,
            "max": 4500.0
        },
        {
            "current": 1237.361,
            "min": 400.0,
            "max": 4500.0
        }
    ],
    "disk": {
        "total": 446.36768341064453,
        "used": 325.6005058288574
    },
    "memory": {
        "total": 15.319561004638672
    }
}
